[
 {
  "table":"TADIR",
  "data":
  [
   {
    "PGMID":"R3TR",
    "OBJECT":"SUSH",
    "OBJ_NAME":"50F0B419B4931AAA55159A5CF0EEBFHT",
    "KORRNUM":"",
    "SRCSYSTEM":"...",
    "AUTHOR":"SAP_CUSTOMER",
    "SRCDEP":"",
    "DEVCLASS":"YNFT_IMPORT",
    "GENFLAG":"",
    "EDTFLAG":"",
    "CPROJECT":" L",
    "MASTERLANG":"T",
    "VERSID":"",
    "PAKNOCHECK":"",
    "OBJSTABLTY":"",
    "COMPONENT":"",
    "CRELEASE":"",
    "DELFLAG":"",
    "TRANSLTTXT":"",
    "CREATED_ON":"2024-05-21",
    "CHECK_DATE":"2024-05-21",
    "CHECK_CFG":""
   }
  ]
 },
 {
  "table":"USOBHASH",
  "data":
  [
   {
    "NAME":"50F0B419B4931AAA55159A5CF0EEBF",
    "TYPE":"HT",
    "PGMID":"R3TR",
    "OBJECT":"IWSV",
    "OBJ_NAME":"YSB_NFT_FIORI_VALUE_HELP           0001",
    "SERVICE_TYPE":"",
    "SERVICE":""
   }
  ]
 },
 {
  "table":"USOBX",
  "data":
  [
   {
    "NAME":"50F0B419B4931AAA55159A5CF0EEBF",
    "TYPE":"HT",
    "OBJECT":"S_SERVICE",
    "MODIFIER":"SAP_CUSTOMER",
    "MODDATE":"2024-05-21",
    "MODTIME":"13:18:05",
    "OKFLAG":"X"
   }
  ]
 },
 {
  "table":"USOB_SM",
  "data":
  [
   {
    "NAME":"50F0B419B4931AAA55159A5CF0EEBF",
    "TYPE":"HT",
    "MODIFIER":"SAP_CUSTOMER",
    "MODDATE":"2024-05-21",
    "MODTIME":"13:18:05",
    "OKFLAG":"",
    "ATTRIBUTES":"",
    "ABAP_LANGUAGE_VERSION":"5"
   }
  ]
 }
]