[
 {
  "table":"DD04L",
  "data":
  [
   {
    "ROLLNAME":"YNFT_E_ZTERM",
    "AS4LOCAL":"L",
    "AS4VERS":0,
    "DOMNAME":"",
    "ROUTPUTLEN":0,
    "MEMORYID":"",
    "LOGFLAG":"",
    "HEADLEN":55,
    "SCRLEN1":10,
    "SCRLEN2":20,
    "SCRLEN3":40,
    "ACTFLAG":"",
    "APPLCLASS":"",
    "AUTHCLASS":0,
    "AS4USER":"SAP_CUSTOMER",
    "AS4DATE":"0000-00-00",
    "AS4TIME":"00:00:00",
    "DTELMASTER":"T",
    "RESERVEDTE":"",
    "DTELGLOBAL":"",
    "SHLPNAME":"",
    "SHLPFIELD":"",
    "DEFFDNAME":"",
    "DATATYPE":"CHAR",
    "LENG":4,
    "DECIMALS":0,
    "OUTPUTLEN":4,
    "LOWERCASE":"",
    "SIGNFLAG":"",
    "CONVEXIT":"",
    "VALEXI":"",
    "ENTITYTAB":"",
    "REFKIND":"",
    "REFTYPE":"",
    "PROXYTYPE":"",
    "LTRFLDDIS":"",
    "BIDICTRLC":"",
    "NOHISTORY":"",
    "ABAP_LANGUAGE_VERSION":"5"
   }
  ]
 },
 {
  "table":"DD04T",
  "data":
  [
   {
    "ROLLNAME":"YNFT_E_ZTERM",
    "DDLANGUAGE":"E",
    "AS4LOCAL":"N",
    "AS4VERS":0,
    "DDTEXT":"Payment Terms",
    "REPTEXT":"Payment Terms",
    "SCRTEXT_S":"Pay.Terms",
    "SCRTEXT_M":"Payment Terms",
    "SCRTEXT_L":"Payment Terms"
   },
   {
    "ROLLNAME":"YNFT_E_ZTERM",
    "DDLANGUAGE":"T",
    "AS4LOCAL":"N",
    "AS4VERS":0,
    "DDTEXT":"Ödeme Koşulu",
    "REPTEXT":"Ödeme Koşulu",
    "SCRTEXT_S":"Ödeme Kşl",
    "SCRTEXT_M":"Ödeme Koşulu",
    "SCRTEXT_L":"Ödeme Koşulu"
   }
  ]
 },
 {
  "table":"DDTYPES",
  "data":
  [
   {
    "TYPENAME":"YNFT_E_ZTERM",
    "STATE":"N",
    "TYPEKIND":"DTEL"
   }
  ]
 },
 {
  "table":"TADIR",
  "data":
  [
   {
    "PGMID":"R3TR",
    "OBJECT":"DTEL",
    "OBJ_NAME":"YNFT_E_ZTERM",
    "KORRNUM":"",
    "SRCSYSTEM":"...",
    "AUTHOR":"SAP_CUSTOMER",
    "SRCDEP":"",
    "DEVCLASS":"YNFT_IMPORT",
    "GENFLAG":"",
    "EDTFLAG":"",
    "CPROJECT":" L",
    "MASTERLANG":"T",
    "VERSID":"",
    "PAKNOCHECK":"",
    "OBJSTABLTY":"",
    "COMPONENT":"",
    "CRELEASE":"",
    "DELFLAG":"",
    "TRANSLTTXT":"",
    "CREATED_ON":"2024-05-21",
    "CHECK_DATE":"2024-05-21",
    "CHECK_CFG":""
   }
  ]
 }
]