[
 {
  "table":"SRVDSRC",
  "data":
  [
   {
    "SRVDNAME":"YSD_NFT_T001",
    "VERSION":"A",
    "CHANGED_BY":"SAP_CUSTOMER",
    "CHANGED_ON":"2024-05-21",
    "CHANGED_AT":"12:38:55",
    "DT_UUID":"370E609375501EEF85EDE2B2F7060067",
    "SOURCE_ORIGIN":"0",
    "SRVD_SOURCE_TYPE":"S",
    "ABAP_LANGUAGE_VERSION":"5"
   }
  ]
 },
 {
  "table":"SRVDSRCT",
  "data":
  [
   {
    "SRVDNAME":"YSD_NFT_T001",
    "VERSION":"A",
    "LANGUAGE":"T",
    "DESCRIPTION":"Satınalma Servis Tanımlama"
   }
  ]
 },
 {
  "table":"SRVDSRC_SRC",
  "data":
  [
   {
    "SRVDNAME":"YSD_NFT_T001",
    "VERSION":"A",
    "SOURCE":"@EndUserText.label: 'Satınalma Servis Tanımlama'\r\ndefine service YSD_NFT_T001 {\r\n  expose YC_NFT_DDL_T001 as T001;\r\n  expose YC_NFT_DDL_T002 as T002;\r\n}"
   }
  ]
 },
 {
  "table":"SRVD_RT_ANNOS",
  "data":
  [
   {
    "SRVDNAME":"YSD_NFT_T001",
    "NAME":"ENDUSERTEXT.LABEL",
    "VALUE":"'Satınalma Servis Tanımlama'"
   }
  ]
 },
 {
  "table":"SRVD_RT_ANNOS_T",
  "data":
  [
   {
    "SRVDNAME":"YSD_NFT_T001",
    "LANGUAGE":"T",
    "NAME":"ENDUSERTEXT.LABEL",
    "TEXT":"Satınalma Servis Tanımlama"
   }
  ]
 },
 {
  "table":"SRVD_RT_ENTITIES",
  "data":
  [
   {
    "SRVDNAME":"YSD_NFT_T001",
    "SERVICE":"YSD_NFT_T001",
    "EXPOSED_ARTIFACT":"YC_NFT_DDL_T001",
    "EXPOSED_ARTIFACT_TYPE":"E",
    "EXPOSED_ALIAS":"T001",
    "EXPOSED_ALIAS_RAW":"T001",
    "INCL_SERVICE":""
   },
   {
    "SRVDNAME":"YSD_NFT_T001",
    "SERVICE":"YSD_NFT_T001",
    "EXPOSED_ARTIFACT":"YC_NFT_DDL_T002",
    "EXPOSED_ARTIFACT_TYPE":"E",
    "EXPOSED_ALIAS":"T002",
    "EXPOSED_ALIAS_RAW":"T002",
    "INCL_SERVICE":""
   }
  ]
 },
 {
  "table":"SRVD_RT_HEADER",
  "data":
  [
   {
    "SRVDNAME":"YSD_NFT_T001",
    "SERVICE":"YSD_NFT_T001",
    "SERVICE_RAW":"YSD_NFT_T001",
    "SOURCE_TYPE":"S",
    "DT_UUID":"370E609375501EEF85EDE2B2F7060067",
    "RT_HASH":"DCA2165E52C90F8378825CF7D310ADD62955B6EA",
    "GEN_VERSION":"0"
   }
  ]
 },
 {
  "table":"TADIR",
  "data":
  [
   {
    "PGMID":"R3TR",
    "OBJECT":"SRVD",
    "OBJ_NAME":"YSD_NFT_T001",
    "KORRNUM":"",
    "SRCSYSTEM":"...",
    "AUTHOR":"SAP_CUSTOMER",
    "SRCDEP":"",
    "DEVCLASS":"YNFT_IMPORT",
    "GENFLAG":"",
    "EDTFLAG":"",
    "CPROJECT":" L",
    "MASTERLANG":"T",
    "VERSID":"",
    "PAKNOCHECK":"",
    "OBJSTABLTY":"",
    "COMPONENT":"",
    "CRELEASE":"",
    "DELFLAG":"",
    "TRANSLTTXT":"",
    "CREATED_ON":"2024-05-21",
    "CHECK_DATE":"2024-05-21",
    "CHECK_CFG":""
   }
  ]
 }
]